djtranslationchecker
