Metadata-Version: 1.1
Name: djtranslationchecker
Version: 0.10.1
Summary: Check your Django translation files
Home-page: https://github.com/laterpay/djtranslationchecker
Author: LaterPay GmbH
Author-email: support@laterpay.net
License: MIT
Keywords: Django translation check gettext
Platform: UNKNOWN
Classifier: Development Status :: 4 - Beta
Classifier: Intended Audience :: Developers
Classifier: License :: OSI Approved :: MIT License
Classifier: Operating System :: OS Independent
Classifier: Programming Language :: Python
Classifier: Programming Language :: Python :: 2.7
Classifier: Programming Language :: Python :: 3.3
Classifier: Programming Language :: Python :: 3.4
Classifier: Topic :: Software Development :: Libraries :: Python Modules
